mce_deepeval_adapter/__init__.py
mce_deepeval_adapter/adapter.py
mce_deepeval_adapter/geval_criteria.py
mce_deepeval_adapter/metric_configuration.py
mce_deepeval_adapter/metric_test_case_creation.py
mce_deepeval_adapter/model_loader.py
mce_deepeval_adapter/llms/custom_model.py
mce_deepeval_adapter-0.1.3.dist-info/METADATA
mce_deepeval_adapter-0.1.3.dist-info/WHEEL
mce_deepeval_adapter-0.1.3.dist-info/entry_points.txt
mce_deepeval_adapter-0.1.3.dist-info/RECORD
